code_splitter/__init__.py
code_splitter/astsnowballsplitter.py
astsnowballsplitter-0.2.0.dist-info/METADATA
astsnowballsplitter-0.2.0.dist-info/WHEEL
astsnowballsplitter-0.2.0.dist-info/top_level.txt
astsnowballsplitter-0.2.0.dist-info/RECORD
