Metadata-Version: 2.1
Name: astsnowballsplitter
Version: 0.2.0
Summary: A package for smartly splitting code into chunks
Home-page: https://github.com/ilanaliouchouche/ASTSnowballSplitter
Author: Ilan Aliouchouche
Author-email: ilan.aliouchouche@universite-paris-saclay.fr
Classifier: Programming Language :: Python :: 3
Classifier: License :: OSI Approved :: MIT License
Classifier: Operating System :: OS Independent
Requires-Python: >=3.10
Requires-Dist: tiktoken >=0.7.0
Requires-Dist: transformers >=4.41.2
Requires-Dist: langchain >=0.2.3
Requires-Dist: spacy >=3.7.5
Requires-Dist: tree-sitter >=0.20.1
